{"armature":[{"name":"zhuanchang","animation":[{"fadeInTime":0.3,"name":1,"duration":6,"tweenEasing":null,"timeline":[{"offset":0,"name":"cinao6","scale":1,"frame":[{"tweenEasing":0,"z":0,"transform":{"x":410.3,"skY":0,"y":-491.6,"pX":0,"scX":2,"pY":0,"scY":2,"skX":0},"duration":4},{"duration":1,"z":0,"transform":{"x":-138.3,"skY":0,"y":-491.6,"pX":0,"scX":2,"pY":0,"scY":2,"skX":0}},{"duration":1,"z":0,"transform":{"x":-359.3,"skY":0,"y":-491.6,"pX":0,"scX":2,"pY":0,"scY":2,"skX":0}}]},{"offset":0,"name":"cinao5","scale":1,"frame":[{"tweenEasing":0,"z":1,"transform":{"x":425.85,"skY":-180,"y":-293.7,"pX":0,"scX":-1.71,"pY":0,"scY":1.71,"skX":180},"duration":4},{"duration":1,"z":1,"transform":{"x":-122.75,"skY":-180,"y":-293.7,"pX":0.05,"scX":-1.71,"pY":0,"scY":1.71,"skX":180}},{"duration":1,"z":1,"transform":{"x":-343.75,"skY":-180,"y":-293.7,"pX":0,"scX":-1.71,"pY":0,"scY":1.71,"skX":180}}]},{"offset":0,"name":"cinao4","scale":1,"frame":[{"tweenEasing":0,"z":2,"transform":{"x":392,"skY":0,"y":-71.3,"pX":0,"scX":2.4,"pY":0,"scY":2.4,"skX":0},"duration":4},{"duration":1,"z":2,"transform":{"x":-156.6,"skY":0,"y":-71.3,"pX":0,"scX":2.4,"pY":0,"scY":2.4,"skX":0}},{"duration":1,"z":2,"transform":{"x":-377.6,"skY":0,"y":-71.3,"pX":0,"scX":2.4,"pY":0,"scY":2.4,"skX":0}}]},{"offset":0,"name":"cinao3","scale":1,"frame":[{"tweenEasing":0,"z":3,"transform":{"x":425.85,"skY":-180,"y":146.3,"pX":0,"scX":-1.71,"pY":0,"scY":1.71,"skX":180},"duration":4},{"duration":1,"z":3,"transform":{"x":-122.75,"skY":-180,"y":146.3,"pX":0.05,"scX":-1.71,"pY":0,"scY":1.71,"skX":180}},{"duration":1,"z":3,"transform":{"x":-343.75,"skY":-180,"y":146.3,"pX":0,"scX":-1.71,"pY":0,"scY":1.71,"skX":180}}]},{"offset":0,"name":"cinao2","scale":1,"frame":[{"tweenEasing":0,"z":4,"transform":{"x":412.9,"skY":0,"y":346.6,"pX":0,"scX":2,"pY":0,"scY":2,"skX":0},"duration":4},{"duration":1,"z":4,"transform":{"x":-135.7,"skY":0,"y":346.6,"pX":0,"scX":2,"pY":0,"scY":2,"skX":0}},{"duration":1,"z":4,"transform":{"x":-356.7,"skY":0,"y":346.6,"pX":0,"scX":2,"pY":0,"scY":2,"skX":0}}]},{"offset":0,"name":"cinao1","scale":1,"frame":[{"tweenEasing":0,"z":5,"transform":{"x":425.85,"skY":-180,"y":546.7,"pX":0,"scX":-1.71,"pY":0,"scY":1.71,"skX":180},"duration":4},{"duration":1,"z":5,"transform":{"x":-122.75,"skY":-180,"y":546.7,"pX":0.05,"scX":-1.71,"pY":0,"scY":1.71,"skX":180}},{"duration":1,"z":5,"transform":{"x":-343.75,"skY":-180,"y":546.7,"pX":0,"scX":-1.71,"pY":0,"scY":1.71,"skX":180}}]},{"offset":0,"name":"fang1","scale":1,"frame":[{"tweenEasing":0,"z":6,"transform":{"x":783.65,"skY":0,"y":17.05,"pX":0,"scX":9.27,"pY":0,"scY":11.26,"skX":0},"duration":4},{"duration":1,"z":6,"transform":{"x":235.05,"skY":0,"y":17.05,"pX":0,"scX":9.27,"pY":0,"scY":11.26,"skX":0}},{"duration":1,"z":6,"transform":{"x":55.65,"skY":0,"y":17.05,"pX":0,"scX":9.98,"pY":0,"scY":11.26,"skX":0}}]},{"offset":0,"name":"rongqi","scale":1,"frame":[{"duration":5,"displayIndex":-1},{"event":"rongqi","z":7,"transform":{"x":-4,"skY":0,"y":376,"pX":0,"scX":1,"pY":0,"scY":1,"skX":0},"duration":1}]}],"scale":1,"loop":1,"autoTween":0},{"fadeInTime":0.3,"name":2,"duration":8,"tweenEasing":null,"timeline":[{"offset":0,"name":"cinao6","scale":1,"frame":[{"tweenEasing":0,"z":0,"transform":{"x":425.2,"skY":0,"y":-491.6,"pX":0,"scX":-2,"pY":0,"scY":2,"skX":0},"duration":6},{"duration":1,"z":0,"transform":{"x":-367.8,"skY":0,"y":-491.6,"pX":0,"scX":-2,"pY":0,"scY":2,"skX":0}},{"duration":1,"displayIndex":-1}]},{"offset":0,"name":"cinao5","scale":1,"frame":[{"tweenEasing":0,"z":1,"transform":{"x":409.65,"skY":180,"y":-293.7,"pX":0,"scX":1.71,"pY":0,"scY":1.71,"skX":180},"duration":6},{"duration":1,"z":1,"transform":{"x":-383.35,"skY":180,"y":-293.7,"pX":0,"scX":1.71,"pY":0,"scY":1.71,"skX":180}},{"duration":1,"displayIndex":-1}]},{"offset":0,"name":"cinao4","scale":1,"frame":[{"tweenEasing":0,"z":2,"transform":{"x":443.5,"skY":0,"y":-71.3,"pX":0,"scX":-2.4,"pY":0,"scY":2.4,"skX":0},"duration":6},{"duration":1,"z":2,"transform":{"x":-349.5,"skY":0,"y":-71.3,"pX":0,"scX":-2.4,"pY":0,"scY":2.4,"skX":0}},{"duration":1,"displayIndex":-1}]},{"offset":0,"name":"cinao3","scale":1,"frame":[{"tweenEasing":0,"z":3,"transform":{"x":409.65,"skY":180,"y":146.3,"pX":0,"scX":1.71,"pY":0,"scY":1.71,"skX":180},"duration":6},{"duration":1,"z":3,"transform":{"x":-383.35,"skY":180,"y":146.3,"pX":0,"scX":1.71,"pY":0,"scY":1.71,"skX":180}},{"duration":1,"displayIndex":-1}]},{"offset":0,"name":"cinao2","scale":1,"frame":[{"tweenEasing":0,"z":4,"transform":{"x":422.6,"skY":0,"y":346.6,"pX":0,"scX":-2,"pY":0,"scY":2,"skX":0},"duration":6},{"duration":1,"z":4,"transform":{"x":-370.4,"skY":0,"y":346.6,"pX":0,"scX":-2,"pY":0,"scY":2,"skX":0}},{"duration":1,"displayIndex":-1}]},{"offset":0,"name":"cinao1","scale":1,"frame":[{"tweenEasing":0,"z":5,"transform":{"x":409.65,"skY":180,"y":546.7,"pX":0,"scX":1.71,"pY":0,"scY":1.71,"skX":180},"duration":6},{"duration":1,"z":5,"transform":{"x":-383.35,"skY":180,"y":546.7,"pX":0,"scX":1.71,"pY":0,"scY":1.71,"skX":180}},{"duration":1,"displayIndex":-1}]},{"offset":0,"name":"fang1","scale":1,"frame":[{"tweenEasing":0,"z":6,"transform":{"x":1.05,"skY":0,"y":17.05,"pX":0,"scX":9.97,"pY":0,"scY":11.26,"skX":0},"duration":6},{"duration":1,"z":6,"transform":{"x":-791.95,"skY":0,"y":17.05,"pX":0,"scX":9.97,"pY":0,"scY":11.26,"skX":0}},{"duration":1,"displayIndex":-1}]}],"scale":1,"loop":1,"autoTween":0}],"skin":[{"slot":[{"display":[{"type":"image","name":"zhuanchang_sc/cinao1","transform":{"x":-76,"skY":0,"y":-54.75,"pX":-0.1,"scX":1,"pY":0,"scY":1,"skX":0}}],"name":"cinao6","z":0,"parent":"cinao6"},{"display":[{"type":"image","name":"zhuanchang_sc/cinao1","transform":{"x":-75.95,"skY":0,"y":-54.75,"pX":-0.1,"scX":1,"pY":0,"scY":1,"skX":0}}],"name":"cinao5","z":1,"parent":"cinao5"},{"display":[{"type":"image","name":"zhuanchang_sc/cinao1","transform":{"x":-76,"skY":0,"y":-54.75,"pX":-0.1,"scX":1,"pY":0,"scY":1,"skX":0}}],"name":"cinao4","z":2,"parent":"cinao4"},{"display":[{"type":"image","name":"zhuanchang_sc/cinao1","transform":{"x":-75.95,"skY":0,"y":-54.75,"pX":-0.1,"scX":1,"pY":0,"scY":1,"skX":0}}],"name":"cinao3","z":3,"parent":"cinao3"},{"display":[{"type":"image","name":"zhuanchang_sc/cinao1","transform":{"x":-76,"skY":0,"y":-54.75,"pX":-0.1,"scX":1,"pY":0,"scY":1,"skX":0}}],"name":"cinao2","z":4,"parent":"cinao2"},{"display":[{"type":"image","name":"zhuanchang_sc/cinao1","transform":{"x":-75.95,"skY":0,"y":-54.75,"pX":-0.1,"scX":1,"pY":0,"scY":1,"skX":0}}],"name":"cinao1","z":5,"parent":"cinao1"},{"display":[{"type":"image","name":"zhuanchang_sc/heidi","transform":{"x":0,"skY":0,"y":0,"pX":33,"scX":1,"pY":55,"scY":1,"skX":0}}],"name":"fang1","z":6,"parent":"fang1"},{"name":"rongqi","z":7,"parent":"rongqi"}],"name":"default"}],"bone":[{"transform":{"x":410.3,"skY":0,"y":-491.6,"scX":2,"scY":2,"skX":0},"name":"cinao6"},{"transform":{"x":425.85,"skY":-180,"y":-293.7,"scX":-1.71,"scY":1.71,"skX":180},"name":"cinao5"},{"transform":{"x":392,"skY":0,"y":-71.3,"scX":2.4,"scY":2.4,"skX":0},"name":"cinao4"},{"transform":{"x":425.85,"skY":-180,"y":146.3,"scX":-1.71,"scY":1.71,"skX":180},"name":"cinao3"},{"transform":{"x":412.9,"skY":0,"y":346.6,"scX":2,"scY":2,"skX":0},"name":"cinao2"},{"transform":{"x":425.85,"skY":-180,"y":546.7,"scX":-1.71,"scY":1.71,"skX":180},"name":"cinao1"},{"transform":{"x":783.65,"skY":0,"y":17.05,"scX":9.27,"scY":11.26,"skX":0},"name":"fang1"},{"transform":{"x":-4,"skY":0,"y":376,"scX":1,"scY":1,"skX":0},"name":"rongqi"}]}],"name":"zhuanchang","version":2.3,"frameRate":24}